constrained_types/__init__.py
constrained_types/core.py
constrained_types/helpers.py
constrained_types/primitives.py
constrained_types/py.typed
constrained_types/version.py
constrained_types-0.4.0.dist-info/LICENSE
constrained_types-0.4.0.dist-info/WHEEL
constrained_types-0.4.0.dist-info/METADATA
constrained_types-0.4.0.dist-info/RECORD
