Metadata-Version: 2.1
Name: constrained_types
Version: 0.4.0
Summary: Extensions for primitives to add validation constraints
Home-page: https://github.com/meadsteve/constrained_types/
License: UNKNOWN
Author: meadsteve
Author-email: meadsteve@gmail.com
Requires-Python: ~=3.6
Classifier: License :: OSI Approved :: MIT License
Requires-Dist: typing-extensions; python_version == '3.6' or python_version == '3.7'
